setup.py
lib_yacht/__init__.py
lib_yacht.egg-info/PKG-INFO
lib_yacht.egg-info/SOURCES.txt
lib_yacht.egg-info/dependency_links.txt
lib_yacht.egg-info/top_level.txt